{
   "name" : "@ignf-geoportal/sdk-3d",
   "description" : "French Geoportal SDK based on OpenLayers (2D) and iTowns (3D) libraries",
   "date" : "02/04/2020",
   "module" : "src/SDK3D.js",
   "repository" : {
      "url" : "https://github.com/IGNF/geoportal-sdk.git",
      "type" : "git"
   },
   "dependencies" : {
      "geoportal-extensions-openlayers" : "3.0.10",
      "itowns" : "2.19.0",
      "ol" : "5.3.0",
      "geoportal-extensions-itowns" : "2.2.9"
   },
   "directories" : {},
   "keywords" : [
      "openlayers",
      "itowns",
      "geoportail",
      "webservice",
      "javascript"
   ],
   "license" : "CECILL-B",
   "bugs" : {
      "url" : "https://github.com/IGNF/geoportal-sdk/issues"
   },
   "homepage" : "https://geoservices.ign.fr/documentation/utilisation_web/sdk.html",
   "version" : "3.0.11",
   "main" : "dist/GpSDK3D-src.js",
   "files" : [
      "dist/",
      "src/",
      "LICENCE.md",
      "README.md",
      "package.json"
   ],
   "author" : "IGNF",
   "scripts" : {}
}
