{
   "keywords" : [
      "openlayers",
      "geoportail",
      "webservice",
      "javascript"
   ],
   "date" : "23/11/2023",
   "bugs" : {
      "url" : "https://github.com/IGNF/geoportal-sdk/issues"
   },
   "module" : "src/SDK2D.js",
   "author" : "IGNF",
   "homepage" : "https://geoservices.ign.fr/documentation/utilisation_web/sdk.html",
   "scripts" : {},
   "license" : "CECILL-B",
   "repository" : {
      "type" : "git",
      "url" : "https://github.com/IGNF/geoportal-sdk.git"
   },
   "dependencies" : {
      "xmldom" : "^0.1.27",
      "geoportal-extensions-openlayers" : "3.4.0-beta2",
      "node-fetch" : "^2.6.1",
      "ol" : "6.9.0"
   },
   "main" : "dist/GpSDK2D-src.js",
   "version" : "3.5.0-beta3",
   "description" : "French Geoportal SDK based on OpenLayers (2D)",
   "directories" : {},
   "files" : [
      "dist/",
      "src/",
      "LICENCE.md",
      "README.md",
      "package.json"
   ],
   "name" : "@ignf-geoportal/sdk-2d"
}
