{
   "name" : "@ignf-geoportal/sdk-3d",
   "homepage" : "https://geoservices.ign.fr/documentation/utilisation_web/sdk.html",
   "dependencies" : {
      "ol" : "6.9.0",
      "geoportal-extensions-openlayers" : "3.3.1",
      "itowns" : "2.38.2",
      "geoportal-extensions-itowns" : "2.4.1",
      "node-fetch" : "^2.6.1",
      "xmldom" : "^0.1.27"
   },
   "directories" : {},
   "module" : "src/SDK3D.js",
   "main" : "dist/GpSDK3D-src.js",
   "author" : "IGNF",
   "files" : [
      "dist/",
      "src/",
      "LICENCE.md",
      "README.md",
      "package.json"
   ],
   "description" : "French Geoportal SDK based on OpenLayers (2D) and iTowns (3D) libraries",
   "repository" : {
      "type" : "git",
      "url" : "https://github.com/IGNF/geoportal-sdk.git"
   },
   "version" : "3.4.0",
   "scripts" : {},
   "bugs" : {
      "url" : "https://github.com/IGNF/geoportal-sdk/issues"
   },
   "keywords" : [
      "openlayers",
      "itowns",
      "geoportail",
      "webservice",
      "javascript"
   ],
   "license" : "CECILL-B",
   "date" : "07/06/2023"
}
